mcp_server_fetch/__init__.py
mcp_server_fetch/__main__.py
mcp_server_fetch/__main_sse__.py
mcp_server_fetch/http_sse_server.py
mcp_server_fetch/server.py
mcp_server_fetch/sse_server.py
mcp_server_fetch_sse-0.1.1.dist-info/METADATA
mcp_server_fetch_sse-0.1.1.dist-info/WHEEL
mcp_server_fetch_sse-0.1.1.dist-info/entry_points.txt
mcp_server_fetch_sse-0.1.1.dist-info/licenses/LICENSE
mcp_server_fetch_sse-0.1.1.dist-info/RECORD
